Workbook

Sheet Read Me
A1: Pricing Model — how to read it
A2: Inputs | B2: Change blue cells. Hourly value, agent cost, fees, tooling, volume, two automation levels, and utilization drive everything.
A3: Cost to Serve | B3: How cost falls as the agent handles more. The high-vs-low-automation gap is your real overhead saving.
A4: Tier Margins (Current) | B4: Your live prices at Phase 1 (you deliver) vs Phase 2 (agent delivers), now adjusted for utilization. Red = loss.
A5: Proposed Tiers | B5: A structure that actually works: agent-only $19 on-ramp, human-backed Essential $59, repriced Family $99, $99 per-session, and a temporary $39 founding rate.
A7: KEY INSIGHT
B8: At $150/hr a 60-min human session costs ~$150 to deliver. Consumer prices are PHASE-2 products — profitable only when the agent delivers. In Phase 1 they're a deliberate, time-boxed loss leader. Cap the volume.
A9: UTILIZATION
B10: Monthly margins depend heavily on how many included sessions go unused (breakage). Default 60% utilization. Price to survive worst-case (100% use), profit on breakage — never the reverse.
A11: PASSING SAVINGS
B12: Pass savings ONLY as categories graduate (use the tracker). Hold price + add value where AI is cheap; cut headline price only on the genuinely agent-only tier; use the founding rate to give an early discount without anchoring low.

Sheet Inputs
A1: Pricing Model — Inputs
A2: Edit the highlighted (blue) cells. Everything else recalculates.
A4: Your hourly value (human time) | B4: 150 | C4: $/hr — value of an hour of your time
A5: → Value per minute | B5: =B4/60 -> 2.5 | C5: auto = hourly / 60
A6: Agent cost per case | B6: 1 | C6: AI/API/compute to handle one case
A7: Payment processing fee | B7: 0.03 | C7: card/Stripe ~3%
A8: Tooling — fixed monthly | B8: 200 | C8: Atera + Loki/Hetzner share + misc
A9: Est. monthly case volume | B9: 50 | C9: spreads fixed cost across cases
A10: → Fixed cost per case | B10: =B8/B9 -> 4 | C10: auto = fixed monthly / volume
A11: Default session length (min) | B11: 60 | C11: baseline session duration
A12: Phase 1 automation % (you-heavy) | B12: 0.1 | C12: agent share while you supervise everything
A13: Phase 2 automation % (agent-heavy) | B13: 0.89 | C13: agent share after graduation
A14: Monthly-plan utilization % | B14: 0.6 | C14: share of INCLUDED sessions subscribers actually use (breakage lives here)

Sheet Cost to Serve
A1: Cost to Serve a 60-min Session vs. Automation
A2: As the agent handles more, your time drops out and cost falls. This gap IS the overhead saving — real only once agents deliver.
A4: Automation % | B4: Human minutes | C4: Human cost | D4: Agent cost | E4: Fixed/case | F4: Cost to Serve
A5: 0 | B5: =Inputs!$B$11*(1-A5) -> 60 | C5: =B5*Inputs!$B$5 -> 150 | D5: =Inputs!$B$6 -> 1 | E5: =Inputs!$B$10 -> 4 | F5: =C5+D5+E5 -> 155
A6: 0.1 | B6: =Inputs!$B$11*(1-A6) -> 54 | C6: =B6*Inputs!$B$5 -> 135 | D6: =Inputs!$B$6 -> 1 | E6: =Inputs!$B$10 -> 4 | F6: =C6+D6+E6 -> 140
A7: 0.25 | B7: =Inputs!$B$11*(1-A7) -> 45 | C7: =B7*Inputs!$B$5 -> 112.5 | D7: =Inputs!$B$6 -> 1 | E7: =Inputs!$B$10 -> 4 | F7: =C7+D7+E7 -> 117.5
A8: 0.5 | B8: =Inputs!$B$11*(1-A8) -> 30 | C8: =B8*Inputs!$B$5 -> 75 | D8: =Inputs!$B$6 -> 1 | E8: =Inputs!$B$10 -> 4 | F8: =C8+D8+E8 -> 80
A9: 0.75 | B9: =Inputs!$B$11*(1-A9) -> 15 | C9: =B9*Inputs!$B$5 -> 37.5 | D9: =Inputs!$B$6 -> 1 | E9: =Inputs!$B$10 -> 4 | F9: =C9+D9+E9 -> 42.5
A10: 0.89 | B10: =Inputs!$B$11*(1-A10) -> 6.6 | C10: =B10*Inputs!$B$5 -> 16.5 | D10: =Inputs!$B$6 -> 1 | E10: =Inputs!$B$10 -> 4 | F10: =C10+D10+E10 -> 21.5
A11: 0.95 | B11: =Inputs!$B$11*(1-A11) -> 3 | C11: =B11*Inputs!$B$5 -> 7.5 | D11: =Inputs!$B$6 -> 1 | E11: =Inputs!$B$10 -> 4 | F11: =C11+D11+E11 -> 12.5
A12: 1 | B12: =Inputs!$B$11*(1-A12) -> 0 | C12: =B12*Inputs!$B$5 -> 0 | D12: =Inputs!$B$6 -> 1 | E12: =Inputs!$B$10 -> 4 | F12: =C12+D12+E12 -> 5

Sheet Tier Margins (Current)
A1: Current Prices — Phase 1 vs Phase 2, adjusted for utilization
A2: Total cost now reflects sessions ACTUALLY used (sessions x utilization). Red margin = losing money.
A4: Tier | B4: Price | C4: Billing | D4: Sessions /cycle | E4: Util % | F4: Session min | G4: Cost/sess P1 | H4: Total cost P1 | I4: Fees | J4: Margin $ P1 | K4: Margin % P1 | L4: Cost/sess P2 | M4: Total cost P2 | N4: Margin $ P2 | O4: Margin % P2 | P4: Break-even auto %
A5: One-time session | B5: 75 | C5: one-time | D5: 1 | E5: =1 -> 1 | F5: 60 | G5: =F5*(1-Inputs!$B$12)*Inputs!$B$5+Inputs!$B$6+Inputs!$B$10 -> 140 | H5: =G5*D5*E5 -> 140 | I5: =B5*Inputs!$B$7 -> 2.25 | J5: =B5-H5-I5 -> -67.25 | K5: =J5/B5 -> -0.89666667 | L5: =F5*(1-Inputs!$B$13)*Inputs!$B$5+Inputs!$B$6+Inputs!$B$10 -> 21.5 | M5: =L5*D5*E5 -> 21.5 | N5: =B5-M5-I5 -> 51.25 | O5: =N5/B5 -> 0.68333333 | P5: =1-((B5*(1-Inputs!$B$7)-D5*E5*(Inputs!$B$6+Inputs!$B$10))/(D5*E5*F5*Inputs!$B$5)) -> 0.54833333
A6: Monthly support | B6: 49 | C6: monthly | D6: 2 | E6: =Inputs!$B$14 -> 0.6 | F6: 60 | G6: =F6*(1-Inputs!$B$12)*Inputs!$B$5+Inputs!$B$6+Inputs!$B$10 -> 140 | H6: =G6*D6*E6 -> 168 | I6: =B6*Inputs!$B$7 -> 1.47 | J6: =B6-H6-I6 -> -120.47 | K6: =J6/B6 -> -2.4585714 | L6: =F6*(1-Inputs!$B$13)*Inputs!$B$5+Inputs!$B$6+Inputs!$B$10 -> 21.5 | M6: =L6*D6*E6 -> 25.8 | N6: =B6-M6-I6 -> 21.73 | O6: =N6/B6 -> 0.44346939 | P6: =1-((B6*(1-Inputs!$B$7)-D6*E6*(Inputs!$B$6+Inputs!$B$10))/(D6*E6*F6*Inputs!$B$5)) -> 0.76927778
A7: Family plan | B7: 79 | C7: monthly | D7: 4 | E7: =Inputs!$B$14 -> 0.6 | F7: 60 | G7: =F7*(1-Inputs!$B$12)*Inputs!$B$5+Inputs!$B$6+Inputs!$B$10 -> 140 | H7: =G7*D7*E7 -> 336 | I7: =B7*Inputs!$B$7 -> 2.37 | J7: =B7-H7-I7 -> -259.37 | K7: =J7/B7 -> -3.2831646 | L7: =F7*(1-Inputs!$B$13)*Inputs!$B$5+Inputs!$B$6+Inputs!$B$10 -> 21.5 | M7: =L7*D7*E7 -> 51.6 | N7: =B7-M7-I7 -> 25.03 | O7: =N7/B7 -> 0.31683544 | P7: =1-((B7*(1-Inputs!$B$7)-D7*E7*(Inputs!$B$6+Inputs!$B$10))/(D7*E7*F7*Inputs!$B$5)) -> 0.82047222
A8: AI-first self-serve (old idea) | B8: 25 | C8: monthly | D8: 4 | E8: =Inputs!$B$14 -> 0.6 | F8: 30 | G8: =F8*(1-Inputs!$B$12)*Inputs!$B$5+Inputs!$B$6+Inputs!$B$10 -> 72.5 | H8: =G8*D8*E8 -> 174 | I8: =B8*Inputs!$B$7 -> 0.75 | J8: =B8-H8-I8 -> -149.75 | K8: =J8/B8 -> -5.99 | L8: =F8*(1-Inputs!$B$13)*Inputs!$B$5+Inputs!$B$6+Inputs!$B$10 -> 13.25 | M8: =L8*D8*E8 -> 31.8 | N8: =B8-M8-I8 -> -7.55 | O8: =N8/B8 -> -0.302 | P8: =1-((B8*(1-Inputs!$B$7)-D8*E8*(Inputs!$B$6+Inputs!$B$10))/(D8*E8*F8*Inputs!$B$5)) -> 0.93194444

Sheet Proposed Tiers
A1: Proposed Tier Structure — built for agent delivery
A2: Each tier priced for its real automation level. Agent-only entry tier is cheap because it IS low-overhead. Founding rate is explicitly temporary.
A4: Tier | B4: Price | C4: Billing | D4: Sessions /cycle | E4: Util % | F4: Session min | G4: Automation % | H4: Cost/sess | I4: Total cost | J4: Fees | K4: Margin $ | L4: Margin % | M4: Notes
A5: AI Chat (agent-only) | B5: 19 | C5: monthly | D5: 8 | E5: =0.5 -> 0.5 | F5: 10 | G5: =1 -> 1 | H5: =F5*(1-G5)*Inputs!$B$5+Inputs!$B$6+Inputs!$B$10 -> 5 | I5: =H5*D5*E5 -> 20 | J5: =B5*Inputs!$B$7 -> 0.57 | K5: =B5-I5-J5 -> -1.57 | L5: =K5/B5 -> -0.082631579 | M5: Unlimited chat modeled as 8 agent touches/mo. Cheap because it's truly low-overhead. The on-ramp for people who can't pay more.
A6: Essential (human-backed) | B6: 59 | C6: monthly | D6: 2 | E6: =Inputs!$B$14 -> 0.6 | F6: 60 | G6: =Inputs!$B$13 -> 0.89 | H6: =F6*(1-G6)*Inputs!$B$5+Inputs!$B$6+Inputs!$B$10 -> 21.5 | I6: =H6*D6*E6 -> 25.8 | J6: =B6*Inputs!$B$7 -> 1.77 | K6: =B6-I6-J6 -> 31.43 | L6: =K6/B6 -> 0.53271186 | M6: AI-first, certified human on escalation. Hold price, add 24/7 + unlimited quick questions.
A7: Family | B7: 99 | C7: monthly | D7: 4 | E7: =Inputs!$B$14 -> 0.6 | F7: 60 | G7: =Inputs!$B$13 -> 0.89 | H7: =F7*(1-G7)*Inputs!$B$5+Inputs!$B$6+Inputs!$B$10 -> 21.5 | I7: =H7*D7*E7 -> 51.6 | J7: =B7*Inputs!$B$7 -> 2.97 | K7: =B7-I7-J7 -> 44.43 | L7: =K7/B7 -> 0.44878788 | M7: Repriced from $79 — $79 was underwater even fully automated. $99 covers worst-case, profits on breakage.
A8: Per-session | B8: 99 | C8: one-time | D8: 1 | E8: =1 -> 1 | F8: 60 | G8: =Inputs!$B$13 -> 0.89 | H8: =F8*(1-G8)*Inputs!$B$5+Inputs!$B$6+Inputs!$B$10 -> 21.5 | I8: =H8*D8*E8 -> 21.5 | J8: =B8*Inputs!$B$7 -> 2.97 | K8: =B8-I8-J8 -> 74.53 | L8: =K8/B8 -> 0.75282828 | M8: Raised from $75. No-commitment rate should sit ABOVE the monthly per-session equivalent to push subscriptions.
A9: Founding rate — Essential (6 mo) | B9: 39 | C9: monthly | D9: 2 | E9: =Inputs!$B$14 -> 0.6 | F9: 60 | G9: =Inputs!$B$13 -> 0.89 | H9: =F9*(1-G9)*Inputs!$B$5+Inputs!$B$6+Inputs!$B$10 -> 21.5 | I9: =H9*D9*E9 -> 25.8 | J9: =B9*Inputs!$B$7 -> 1.17 | K9: =B9-I9-J9 -> 12.03 | L9: =K9/B9 -> 0.30846154 | M9: TEMPORARY. First 50 clients, 6 months, then reverts to $59. Lets you 'pass savings' now without anchoring low.
